iqm/cpc/__init__.py
iqm/cpc/py.typed
iqm/cpc/compiler/__init__.py
iqm/cpc/compiler/compiler.py
iqm/cpc/compiler/dd.py
iqm/cpc/compiler/errors.py
iqm/cpc/compiler/standard_stages.py
iqm/cpc/compiler/station_settings.py
iqm/cpc/interface/__init__.py
iqm/cpc/interface/compiler.py
iqm/pulla/__init__.py
iqm/pulla/calibration.py
iqm/pulla/interface.py
iqm/pulla/pulla.py
iqm/pulla/py.typed
iqm/pulla/quantum_architecture.py
iqm/pulla/utils.py
iqm/pulla/utils_cirq.py
iqm/pulla/utils_dd.py
iqm/pulla/utils_qir.py
iqm/pulla/utils_qiskit.py
iqm_pulla-12.0.3.dist-info/AUTHORS.rst
iqm_pulla-12.0.3.dist-info/LICENSE.txt
iqm_pulla-12.0.3.dist-info/METADATA
iqm_pulla-12.0.3.dist-info/WHEEL
iqm_pulla-12.0.3.dist-info/top_level.txt
iqm_pulla-12.0.3.dist-info/RECORD
