Metadata-Version: 2.1
Name: iqm-pulla
Version: 12.0.3
Summary: Client library for pulse-level access to an IQM quantum computer
Author-email: IQM Finland Oy <developers@meetiqm.com>
License: Apache License
Project-URL: Documentation, https://docs.meetiqm.com/iqm-pulla/
Project-URL: Homepage, https://pypi.org/project/iqm-pulla/
Classifier: Development Status :: 4 - Beta
Classifier: Programming Language :: Python :: 3 :: Only
Classifier: Topic :: Scientific/Engineering :: Physics
Classifier: Intended Audience :: Science/Research
Classifier: License :: OSI Approved :: Apache Software License
Requires-Python: <3.13,>=3.11
License-File: LICENSE.txt
License-File: AUTHORS.rst
Requires-Dist: iqm-data-definitions <3.0,>=2.18
Requires-Dist: pylatexenc ==2.10
Requires-Dist: pydantic <3.0,>=2.10.4
Requires-Dist: iqm-client <34,>=33.0.3
Requires-Dist: iqm-exa-common <28,>=27.4.3
Requires-Dist: iqm-pulse <13,>=12.7.3
Requires-Dist: iqm-station-control-client <13,>=12.0.3
Provides-Extra: notebook
Requires-Dist: notebook <7,>=6.4.11 ; extra == 'notebook'
Requires-Dist: matplotlib <4,>=3.6.3 ; extra == 'notebook'
Requires-Dist: nbclient ~=0.5.10 ; extra == 'notebook'
Provides-Extra: qir
Requires-Dist: iqm-pyqir ==0.12.0 ; extra == 'qir'
Requires-Dist: qiskit <2.2,>=1.0 ; extra == 'qir'
Provides-Extra: qiskit
Requires-Dist: iqm-client[qiskit] <34,>=33.0.3 ; extra == 'qiskit'
